[{
  "_id": {
    "$oid": "6092da0ada6f1c1cecc5ae36"
  },
  "shifts": [
    {
      "$oid": "6092d5c34e48000e8c3a5216"
    },
    {
      "$oid": "6092d5f257b8813844ad433e"
    }
  ],
  "dentist": {
    "$oid": "6092a8da260dfe075c02cf61"
  },
  "day": 28,
  "year": 2021,
  "month": 6
},{
  "_id": {
    "$oid": "6093997243656c057876664f"
  },
  "shifts": [
    {
      "$oid": "6092d5c34e48000e8c3a5216"
    },
    {
      "$oid": "6092d5f257b8813844ad433e"
    }
  ],
  "dentist": {
    "$oid": "6092a23d260dfe075c02cf5e"
  },
  "day": 29,
  "year": 2021,
  "month": 6
},{
  "_id": {
    "$oid": "6093998843656c0578766650"
  },
  "shifts": [
    {
      "$oid": "6092d5c34e48000e8c3a5216"
    },
    {
      "$oid": "6092d5f257b8813844ad433e"
    }
  ],
  "dentist": {
    "$oid": "6092a86a260dfe075c02cf5f"
  },
  "day": 28,
  "year": 2021,
  "month": 6
}]